[
  {
    "inputs": [],
    "name": "AccountNotScored",
    "type": "error"
  },
  {
    "inputs": [],
    "name": "BatchLengthMismatch",
    "type": "error"
  },
  {
    "inputs": [],
    "name": "InvalidScoreRange",
    "type": "error"
  },
  {
    "inputs": [
      {
        "internalType": "address",
        "name": "owner",
        "type": "address"
      }
    ],
    "name": "OwnableInvalidOwner",
    "type": "error"
  },
  {
    "inputs": [
      {
        "internalType": "address",
        "name": "account",
        "type": "address"
      }
    ],
    "name": "OwnableUnauthorizedAccount",
    "type": "error"
  },
  {
    "inputs": [],
    "name": "ScoreExpired",
    "type": "error"
  },
  {
    "inputs": [],
    "name": "UnauthorizedOracle",
    "type": "error"
  },
  {
    "inputs": [],
    "name": "ZamaProtocolUnsupported",
    "type": "error"
  },
  {
    "inputs": [],
    "name": "ZeroAddress",
    "type": "error"
  },
  {
    "anonymous": false,
    "inputs": [
      {
        "indexed": true,
        "internalType": "address",
        "name": "oracle",
        "type": "address"
      },
      {
        "indexed": false,
        "internalType": "bool",
        "name": "authorized",
        "type": "bool"
      }
    ],
    "name": "OracleAuthorized",
    "type": "event"
  },
  {
    "anonymous": false,
    "inputs": [
      {
        "indexed": true,
        "internalType": "address",
        "name": "previousOwner",
        "type": "address"
      },
      {
        "indexed": true,
        "internalType": "address",
        "name": "newOwner",
        "type": "address"
      }
    ],
    "name": "OwnershipTransferStarted",
    "type": "event"
  },
  {
    "anonymous": false,
    "inputs": [
      {
        "indexed": true,
        "internalType": "address",
        "name": "previousOwner",
        "type": "address"
      },
      {
        "indexed": true,
        "internalType": "address",
        "name": "newOwner",
        "type": "address"
      }
    ],
    "name": "OwnershipTransferred",
    "type": "event"
  },
  {
    "anonymous": false,
    "inputs": [
      {
        "indexed": true,
        "internalType": "address",
        "name": "account",
        "type": "address"
      },
      {
        "indexed": true,
        "internalType": "address",
        "name": "allowedAddress",
        "type": "address"
      }
    ],
    "name": "ScoreAccessGranted",
    "type": "event"
  },
  {
    "anonymous": false,
    "inputs": [
      {
        "indexed": true,
        "internalType": "address",
        "name": "account",
        "type": "address"
      }
    ],
    "name": "TrustScoreRevoked",
    "type": "event"
  },
  {
    "anonymous": false,
    "inputs": [
      {
        "indexed": true,
        "internalType": "address",
        "name": "account",
        "type": "address"
      },
      {
        "indexed": false,
        "internalType": "uint256",
        "name": "timestamp",
        "type": "uint256"
      }
    ],
    "name": "TrustScoreUpdated",
    "type": "event"
  },
  {
    "inputs": [],
    "name": "HIGH_TRUST_THRESHOLD",
    "outputs": [
      {
        "internalType": "uint64",
        "name": "",
        "type": "uint64"
      }
    ],
    "stateMutability": "view",
    "type": "function"
  },
  {
    "inputs": [],
    "name": "MAX_SCORE",
    "outputs": [
      {
        "internalType": "uint64",
        "name": "",
        "type": "uint64"
      }
    ],
    "stateMutability": "view",
    "type": "function"
  },
  {
    "inputs": [],
    "name": "MEDIUM_TRUST_THRESHOLD",
    "outputs": [
      {
        "internalType": "uint64",
        "name": "",
        "type": "uint64"
      }
    ],
    "stateMutability": "view",
    "type": "function"
  },
  {
    "inputs": [],
    "name": "SCORE_EXPIRY",
    "outputs": [
      {
        "internalType": "uint256",
        "name": "",
        "type": "uint256"
      }
    ],
    "stateMutability": "view",
    "type": "function"
  },
  {
    "inputs": [],
    "name": "acceptOwnership",
    "outputs": [],
    "stateMutability": "nonpayable",
    "type": "function"
  },
  {
    "inputs": [
      {
        "internalType": "address",
        "name": "account",
        "type": "address"
      },
      {
        "internalType": "address",
        "name": "allowedAddress",
        "type": "address"
      }
    ],
    "name": "allowScoreAccess",
    "outputs": [],
    "stateMutability": "nonpayable",
    "type": "function"
  },
  {
    "inputs": [
      {
        "internalType": "address",
        "name": "",
        "type": "address"
      }
    ],
    "name": "authorizedOracles",
    "outputs": [
      {
        "internalType": "bool",
        "name": "",
        "type": "bool"
      }
    ],
    "stateMutability": "view",
    "type": "function"
  },
  {
    "inputs": [
      {
        "internalType": "address[]",
        "name": "accounts",
        "type": "address[]"
      },
      {
        "internalType": "uint64[]",
        "name": "scores",
        "type": "uint64[]"
      }
    ],
    "name": "batchSetScores",
    "outputs": [],
    "stateMutability": "nonpayable",
    "type": "function"
  },
  {
    "inputs": [],
    "name": "confidentialProtocolId",
    "outputs": [
      {
        "internalType": "uint256",
        "name": "",
        "type": "uint256"
      }
    ],
    "stateMutability": "view",
    "type": "function"
  },
  {
    "inputs": [
      {
        "internalType": "address",
        "name": "account",
        "type": "address"
      }
    ],
    "name": "getTrustScore",
    "outputs": [
      {
        "internalType": "euint64",
        "name": "score",
        "type": "bytes32"
      }
    ],
    "stateMutability": "view",
    "type": "function"
  },
  {
    "inputs": [
      {
        "internalType": "address",
        "name": "account",
        "type": "address"
      }
    ],
    "name": "getTrustTier",
    "outputs": [
      {
        "internalType": "euint64",
        "name": "tier",
        "type": "bytes32"
      }
    ],
    "stateMutability": "nonpayable",
    "type": "function"
  },
  {
    "inputs": [
      {
        "internalType": "address",
        "name": "account",
        "type": "address"
      }
    ],
    "name": "hasScore",
    "outputs": [
      {
        "internalType": "bool",
        "name": "",
        "type": "bool"
      }
    ],
    "stateMutability": "view",
    "type": "function"
  },
  {
    "inputs": [
      {
        "internalType": "address",
        "name": "account",
        "type": "address"
      }
    ],
    "name": "isHighTrust",
    "outputs": [
      {
        "internalType": "ebool",
        "name": "result",
        "type": "bytes32"
      }
    ],
    "stateMutability": "nonpayable",
    "type": "function"
  },
  {
    "inputs": [
      {
        "internalType": "address",
        "name": "account",
        "type": "address"
      }
    ],
    "name": "isLowTrust",
    "outputs": [
      {
        "internalType": "ebool",
        "name": "result",
        "type": "bytes32"
      }
    ],
    "stateMutability": "nonpayable",
    "type": "function"
  },
  {
    "inputs": [
      {
        "internalType": "address",
        "name": "account",
        "type": "address"
      }
    ],
    "name": "isMediumTrust",
    "outputs": [
      {
        "internalType": "ebool",
        "name": "result",
        "type": "bytes32"
      }
    ],
    "stateMutability": "nonpayable",
    "type": "function"
  },
  {
    "inputs": [
      {
        "internalType": "address",
        "name": "account",
        "type": "address"
      }
    ],
    "name": "isScoreExpired",
    "outputs": [
      {
        "internalType": "bool",
        "name": "",
        "type": "bool"
      }
    ],
    "stateMutability": "view",
    "type": "function"
  },
  {
    "inputs": [
      {
        "internalType": "address",
        "name": "",
        "type": "address"
      }
    ],
    "name": "lastScoreUpdate",
    "outputs": [
      {
        "internalType": "uint256",
        "name": "",
        "type": "uint256"
      }
    ],
    "stateMutability": "view",
    "type": "function"
  },
  {
    "inputs": [],
    "name": "owner",
    "outputs": [
      {
        "internalType": "address",
        "name": "",
        "type": "address"
      }
    ],
    "stateMutability": "view",
    "type": "function"
  },
  {
    "inputs": [],
    "name": "pendingOwner",
    "outputs": [
      {
        "internalType": "address",
        "name": "",
        "type": "address"
      }
    ],
    "stateMutability": "view",
    "type": "function"
  },
  {
    "inputs": [],
    "name": "renounceOwnership",
    "outputs": [],
    "stateMutability": "nonpayable",
    "type": "function"
  },
  {
    "inputs": [
      {
        "internalType": "address",
        "name": "account",
        "type": "address"
      }
    ],
    "name": "revokeScore",
    "outputs": [],
    "stateMutability": "nonpayable",
    "type": "function"
  },
  {
    "inputs": [
      {
        "internalType": "address",
        "name": "oracle",
        "type": "address"
      },
      {
        "internalType": "bool",
        "name": "authorized",
        "type": "bool"
      }
    ],
    "name": "setOracle",
    "outputs": [],
    "stateMutability": "nonpayable",
    "type": "function"
  },
  {
    "inputs": [
      {
        "internalType": "address",
        "name": "account",
        "type": "address"
      },
      {
        "internalType": "externalEuint64",
        "name": "encryptedScore",
        "type": "bytes32"
      },
      {
        "internalType": "bytes",
        "name": "inputProof",
        "type": "bytes"
      }
    ],
    "name": "setTrustScore",
    "outputs": [],
    "stateMutability": "nonpayable",
    "type": "function"
  },
  {
    "inputs": [
      {
        "internalType": "address",
        "name": "account",
        "type": "address"
      },
      {
        "internalType": "uint64",
        "name": "score",
        "type": "uint64"
      }
    ],
    "name": "setTrustScorePlaintext",
    "outputs": [],
    "stateMutability": "nonpayable",
    "type": "function"
  },
  {
    "inputs": [],
    "name": "totalScoredAddresses",
    "outputs": [
      {
        "internalType": "uint256",
        "name": "",
        "type": "uint256"
      }
    ],
    "stateMutability": "view",
    "type": "function"
  },
  {
    "inputs": [
      {
        "internalType": "address",
        "name": "newOwner",
        "type": "address"
      }
    ],
    "name": "transferOwnership",
    "outputs": [],
    "stateMutability": "nonpayable",
    "type": "function"
  }
]